{"version":1,"resource":"file:///mnt/windows/LaTeX/HelloWorld.tex","entries":[{"id":"MEUM.tex","source":"textFileCreate.source","timestamp":1693691209529},{"id":"O0Iq.tex","timestamp":1693691213942},{"id":"hurH.tex","timestamp":1693692139698},{"id":"HSEJ.tex","timestamp":1693693171745},{"id":"vVK0.tex","timestamp":1693695178613},{"id":"pMGR.tex","timestamp":1693695690142},{"id":"EeDc.tex","timestamp":1693695731151},{"id":"igQe.tex","timestamp":1693695750115},{"id":"xv99.tex","timestamp":1693695780761},{"id":"CJFU.tex","timestamp":1693769617159},{"id":"w9jj.tex","timestamp":1693794660278},{"id":"tBw6.tex","timestamp":1693794687747},{"id":"lDyI.tex","timestamp":1693794700503},{"id":"HCt9.tex","timestamp":1693794724118},{"id":"s2N4.tex","timestamp":1693794761177},{"id":"XM9B.tex","timestamp":1693794830848},{"id":"bCT1.tex","timestamp":1693794929439},{"id":"uaVa.tex","timestamp":1693794945782},{"id":"reRp.tex","source":"undoRedo.source","timestamp":1693794950047},{"id":"cMsT.tex","timestamp":1693794991244},{"id":"cqZO.tex","timestamp":1693795072427},{"id":"p2OK.tex","timestamp":1693795115583},{"id":"p9Kf.tex","timestamp":1693795149834},{"id":"7Ft6.tex","timestamp":1693795173220},{"id":"Cwnn.tex","timestamp":1693795255442},{"id":"jcim.tex","timestamp":1693795268699}]}